{
	"cmake" : 
	{
		"generator" : 
		{
			"multiConfig" : false,
			"name" : "Ninja"
		},
		"paths" : 
		{
			"cmake" : "/home/vkoliadenko/tools/qt/Tools/CMake/bin/cmake",
			"cpack" : "/home/vkoliadenko/tools/qt/Tools/CMake/bin/cpack",
			"ctest" : "/home/vkoliadenko/tools/qt/Tools/CMake/bin/ctest",
			"root" : "/home/vkoliadenko/tools/qt/Tools/CMake/share/cmake-3.24"
		},
		"version" : 
		{
			"isDirty" : false,
			"major" : 3,
			"minor" : 24,
			"patch" : 2,
			"string" : "3.24.2",
			"suffix" : ""
		}
	},
	"objects" : 
	[
		{
			"jsonFile" : "codemodel-v2-aa5ae0880510de82bf16.json",
			"kind" : "codemodel",
			"version" : 
			{
				"major" : 2,
				"minor" : 4
			}
		},
		{
			"jsonFile" : "cache-v2-6a23cc1b405e060feb01.json",
			"kind" : "cache",
			"version" : 
			{
				"major" : 2,
				"minor" : 0
			}
		},
		{
			"jsonFile" : "cmakeFiles-v1-da3757198b5aca370509.json",
			"kind" : "cmakeFiles",
			"version" : 
			{
				"major" : 1,
				"minor" : 0
			}
		}
	],
	"reply" : 
	{
		"cache-v2" : 
		{
			"jsonFile" : "cache-v2-6a23cc1b405e060feb01.json",
			"kind" : "cache",
			"version" : 
			{
				"major" : 2,
				"minor" : 0
			}
		},
		"cmakeFiles-v1" : 
		{
			"jsonFile" : "cmakeFiles-v1-da3757198b5aca370509.json",
			"kind" : "cmakeFiles",
			"version" : 
			{
				"major" : 1,
				"minor" : 0
			}
		},
		"codemodel-v2" : 
		{
			"jsonFile" : "codemodel-v2-aa5ae0880510de82bf16.json",
			"kind" : "codemodel",
			"version" : 
			{
				"major" : 2,
				"minor" : 4
			}
		}
	}
}
